ccy/__init__.py
ccy/cli/__init__.py
ccy/cli/console.py
ccy/core/__init__.py
ccy/core/country.py
ccy/core/currency.py
ccy/core/data.py
ccy/core/daycounter.py
ccy/dates/__init__.py
ccy/dates/converters.py
ccy/dates/futures.py
ccy/dates/period.py
ccy/dates/utils.py
ccy/py.typed
ccy/tradingcentres/__init__.py
ccy-1.7.2.dist-info/METADATA
ccy-1.7.2.dist-info/WHEEL
ccy-1.7.2.dist-info/entry_points.txt
ccy-1.7.2.dist-info/licenses/LICENSE
ccy-1.7.2.dist-info/RECORD
