Metadata-Version: 2.4
Name: ccy
Version: 1.7.2
Summary: Python currencies
License: BSD
License-File: LICENSE
Author: Luca Sbardella
Author-email: luca@quantmind.com
Requires-Python: >=3.10
Classifier: License :: Other/Proprietary License
Classifier: Programming Language :: Python :: 3
Classifier: Programming Language :: Python :: 3.10
Classifier: Programming Language :: Python :: 3.11
Classifier: Programming Language :: Python :: 3.12
Classifier: Programming Language :: Python :: 3.13
Classifier: Programming Language :: Python :: 3.14
Provides-Extra: cli
Provides-Extra: holidays
Requires-Dist: click (>=8.1.7,<9.0.0) ; extra == "cli"
Requires-Dist: holidays (>=0.63,<0.64) ; extra == "holidays"
Requires-Dist: pandas (>=2.0.3,<3.0.0) ; extra == "cli"
Requires-Dist: pycountry (>=24.6.1,<25.0.0)
Requires-Dist: python-dateutil (>=2.9.0,<3.0.0)
Requires-Dist: rich (>=13.7.1,<14.0.0) ; extra == "cli"
